sphinx_navtree
