Metadata-Version: 1.1
Name: sphinx-navtree
Version: 0.3.0
Summary: Navigation tree customization for Sphinx
Home-page: https://github.com/bintoro/sphinx-navtree
Author: Kalle Tuure
Author-email: kalle@goodtimes.fi
License: MIT
Platform: UNKNOWN
Classifier: Framework :: Sphinx
Classifier: Framework :: Sphinx :: Extension
Classifier: License :: OSI Approved :: MIT License
Classifier: Programming Language :: Python
Classifier: Programming Language :: Python :: 2
Classifier: Programming Language :: Python :: 3
Classifier: Topic :: Documentation
Classifier: Topic :: Documentation :: Sphinx
Classifier: Topic :: Software Development :: Documentation
